[
  { "year": "1959", "month": 1, "value": 138.89 },
  { "year": "1959", "month": 2, "value": 139.39 },
  { "year": "1959", "month": 3, "value": 139.74 },
  { "year": "1959", "month": 4, "value": 139.69 },
  { "year": "1959", "month": 5, "value": 140.68 },
  { "year": "1959", "month": 6, "value": 141.17 },
  { "year": "1959", "month": 7, "value": 141.7 },
  { "year": "1959", "month": 8, "value": 141.9 },
  { "year": "1959", "month": 9, "value": 141.01 },
  { "year": "1959", "month": 10, "value": 140.47 },
  { "year": "1959", "month": 11, "value": 140.38 },
  { "year": "1959", "month": 12, "value": 139.95 },
  { "year": "1960", "month": 1, "value": 139.98 },
  { "year": "1960", "month": 2, "value": 139.87 },
  { "year": "1960", "month": 3, "value": 139.75 },
  { "year": "1960", "month": 4, "value": 139.56 },
  { "year": "1960", "month": 5, "value": 139.61 },
  { "year": "1960", "month": 6, "value": 139.58 },
  { "year": "1960", "month": 7, "value": 140.18 },
  { "year": "1960", "month": 8, "value": 141.31 },
  { "year": "1960", "month": 9, "value": 141.18 },
  { "year": "1960", "month": 10, "value": 140.92 },
  { "year": "1960", "month": 11, "value": 140.86 },
  { "year": "1960", "month": 12, "value": 140.69 },
  { "year": "1961", "month": 1, "value": 141.06 },
  { "year": "1961", "month": 2, "value": 141.6 },
  { "year": "1961", "month": 3, "value": 141.87 },
  { "year": "1961", "month": 4, "value": 142.13 },
  { "year": "1961", "month": 5, "value": 142.66 },
  { "year": "1961", "month": 6, "value": 142.88 },
  { "year": "1961", "month": 7, "value": 142.92 },
  { "year": "1961", "month": 8, "value": 143.49 },
  { "year": "1961", "month": 9, "value": 143.78 },
  { "year": "1961", "month": 10, "value": 144.14 },
  { "year": "1961", "month": 11, "value": 144.76 },
  { "year": "1961", "month": 12, "value": 145.2 },
  { "year": "1962", "month": 1, "value": 145.24 },
  { "year": "1962", "month": 2, "value": 145.66 },
  { "year": "1962", "month": 3, "value": 145.96 },
  { "year": "1962", "month": 4, "value": 146.4 },
  { "year": "1962", "month": 5, "value": 146.84 },
  { "year": "1962", "month": 6, "value": 146.58 },
  { "year": "1962", "month": 7, "value": 146.46 },
  { "year": "1962", "month": 8, "value": 146.57 },
  { "year": "1962", "month": 9, "value": 146.3 },
  { "year": "1962", "month": 10, "value": 146.71 },
  { "year": "1962", "month": 11, "value": 147.29 },
  { "year": "1962", "month": 12, "value": 147.82 },
  { "year": "1963", "month": 1, "value": 148.26 },
  { "year": "1963", "month": 2, "value": 148.9 },
  { "year": "1963", "month": 3, "value": 149.17 },
  { "year": "1963", "month": 4, "value": 149.7 },
  { "year": "1963", "month": 5, "value": 150.39 },
  { "year": "1963", "month": 6, "value": 150.43 },
  { "year": "1963", "month": 7, "value": 151.34 },
  { "year": "1963", "month": 8, "value": 151.78 },
  { "year": "1963", "month": 9, "value": 151.98 },
  { "year": "1963", "month": 10, "value": 152.55 },
  { "year": "1963", "month": 11, "value": 153.65 },
  { "year": "1963", "month": 12, "value": 153.29 },
  { "year": "1964", "month": 1, "value": 153.74 },
  { "year": "1964", "month": 2, "value": 154.31 },
  { "year": "1964", "month": 3, "value": 154.48 },
  { "year": "1964", "month": 4, "value": 154.77 },
  { "year": "1964", "month": 5, "value": 155.33 },
  { "year": "1964", "month": 6, "value": 155.62 },
  { "year": "1964", "month": 7, "value": 156.8 },
  { "year": "1964", "month": 8, "value": 157.82 },
  { "year": "1964", "month": 9, "value": 158.75 },
  { "year": "1964", "month": 10, "value": 159.24 },
  { "year": "1964", "month": 11, "value": 159.96 },
  { "year": "1964", "month": 12, "value": 160.3 },
  { "year": "1965", "month": 1, "value": 160.71 },
  { "year": "1965", "month": 2, "value": 160.94 },
  { "year": "1965", "month": 3, "value": 161.47 },
  { "year": "1965", "month": 4, "value": 162.03 },
  { "year": "1965", "month": 5, "value": 161.7 },
  { "year": "1965", "month": 6, "value": 162.19 },
  { "year": "1965", "month": 7, "value": 163.05 },
  { "year": "1965", "month": 8, "value": 163.68 },
  { "year": "1965", "month": 9, "value": 164.85 },
  { "year": "1965", "month": 10, "value": 165.97 },
  { "year": "1965", "month": 11, "value": 166.71 },
  { "year": "1965", "month": 12, "value": 167.85 },
  { "year": "1966", "month": 1, "value": 169.08 },
  { "year": "1966", "month": 2, "value": 169.62 },
  { "year": "1966", "month": 3, "value": 170.51 },
  { "year": "1966", "month": 4, "value": 171.81 },
  { "year": "1966", "month": 5, "value": 171.33 },
  { "year": "1966", "month": 6, "value": 171.57 },
  { "year": "1966", "month": 7, "value": 170.31 },
  { "year": "1966", "month": 8, "value": 170.81 },
  { "year": "1966", "month": 9, "value": 171.97 },
  { "year": "1966", "month": 10, "value": 171.16 },
  { "year": "1966", "month": 11, "value": 171.38 },
  { "year": "1966", "month": 12, "value": 172.03 },
  { "year": "1967", "month": 1, "value": 171.86 },
  { "year": "1967", "month": 2, "value": 172.99 },
  { "year": "1967", "month": 3, "value": 174.81 },
  { "year": "1967", "month": 4, "value": 174.17 },
  { "year": "1967", "month": 5, "value": 175.68 },
  { "year": "1967", "month": 6, "value": 177.02 },
  { "year": "1967", "month": 7, "value": 178.13 },
  { "year": "1967", "month": 8, "value": 179.71 },
  { "year": "1967", "month": 9, "value": 180.68 },
  { "year": "1967", "month": 10, "value": 181.64 },
  { "year": "1967", "month": 11, "value": 182.38 },
  { "year": "1967", "month": 12, "value": 183.26 },
  { "year": "1968", "month": 1, "value": 184.33 },
  { "year": "1968", "month": 2, "value": 184.71 },
  { "year": "1968", "month": 3, "value": 185.47 },
  { "year": "1968", "month": 4, "value": 186.6 },
  { "year": "1968", "month": 5, "value": 187.99 },
  { "year": "1968", "month": 6, "value": 189.42 },
  { "year": "1968", "month": 7, "value": 190.49 },
  { "year": "1968", "month": 8, "value": 191.84 },
  { "year": "1968", "month": 9, "value": 192.74 },
  { "year": "1968", "month": 10, "value": 194.02 },
  { "year": "1968", "month": 11, "value": 196.02 },
  { "year": "1968", "month": 12, "value": 197.41 },
  { "year": "1969", "month": 1, "value": 198.69 },
  { "year": "1969", "month": 2, "value": 199.35 },
  { "year": "1969", "month": 3, "value": 200.02 },
  { "year": "1969", "month": 4, "value": 200.71 },
  { "year": "1969", "month": 5, "value": 200.81 },
  { "year": "1969", "month": 6, "value": 201.27 },
  { "year": "1969", "month": 7, "value": 201.66 },
  { "year": "1969", "month": 8, "value": 201.73 },
  { "year": "1969", "month": 9, "value": 202.1 },
  { "year": "1969", "month": 10, "value": 202.9 },
  { "year": "1969", "month": 11, "value": 203.57 },
  { "year": "1969", "month": 12, "value": 203.88 },
  { "year": "1970", "month": 1, "value": 206.22 },
  { "year": "1970", "month": 2, "value": 205 },
  { "year": "1970", "month": 3, "value": 205.75 },
  { "year": "1970", "month": 4, "value": 206.72 },
  { "year": "1970", "month": 5, "value": 207.22 },
  { "year": "1970", "month": 6, "value": 207.54 },
  { "year": "1970", "month": 7, "value": 207.98 },
  { "year": "1970", "month": 8, "value": 209.93 },
  { "year": "1970", "month": 9, "value": 211.8 },
  { "year": "1970", "month": 10, "value": 212.88 },
  { "year": "1970", "month": 11, "value": 213.66 },
  { "year": "1970", "month": 12, "value": 214.41 },
  { "year": "1971", "month": 1, "value": 215.54 },
  { "year": "1971", "month": 2, "value": 217.42 },
  { "year": "1971", "month": 3, "value": 218.77 },
  { "year": "1971", "month": 4, "value": 220 },
  { "year": "1971", "month": 5, "value": 222.02 },
  { "year": "1971", "month": 6, "value": 223.45 },
  { "year": "1971", "month": 7, "value": 224.85 },
  { "year": "1971", "month": 8, "value": 225.58 },
  { "year": "1971", "month": 9, "value": 226.47 },
  { "year": "1971", "month": 10, "value": 227.16 },
  { "year": "1971", "month": 11, "value": 227.76 },
  { "year": "1971", "month": 12, "value": 228.32 },
  { "year": "1972", "month": 1, "value": 230.09 },
  { "year": "1972", "month": 2, "value": 232.32 },
  { "year": "1972", "month": 3, "value": 234.3 },
  { "year": "1972", "month": 4, "value": 235.58 },
  { "year": "1972", "month": 5, "value": 235.89 },
  { "year": "1972", "month": 6, "value": 236.62 },
  { "year": "1972", "month": 7, "value": 238.79 },
  { "year": "1972", "month": 8, "value": 240.93 },
  { "year": "1972", "month": 9, "value": 243.18 },
  { "year": "1972", "month": 10, "value": 245.02 },
  { "year": "1972", "month": 11, "value": 246.41 },
  { "year": "1972", "month": 12, "value": 249.25 },
  { "year": "1973", "month": 1, "value": 251.47 },
  { "year": "1973", "month": 2, "value": 252.15 },
  { "year": "1973", "month": 3, "value": 251.67 },
  { "year": "1973", "month": 4, "value": 252.74 },
  { "year": "1973", "month": 5, "value": 254.89 },
  { "year": "1973", "month": 6, "value": 256.69 },
  { "year": "1973", "month": 7, "value": 257.54 },
  { "year": "1973", "month": 8, "value": 257.76 },
  { "year": "1973", "month": 9, "value": 257.86 },
  { "year": "1973", "month": 10, "value": 259.04 },
  { "year": "1973", "month": 11, "value": 260.98 },
  { "year": "1973", "month": 12, "value": 262.88 },
  { "year": "1974", "month": 1, "value": 263.76 },
  { "year": "1974", "month": 2, "value": 265.31 },
  { "year": "1974", "month": 3, "value": 266.68 },
  { "year": "1974", "month": 4, "value": 267.2 },
  { "year": "1974", "month": 5, "value": 267.56 },
  { "year": "1974", "month": 6, "value": 268.44 },
  { "year": "1974", "month": 7, "value": 269.27 },
  { "year": "1974", "month": 8, "value": 270.12 },
  { "year": "1974", "month": 9, "value": 271.05 },
  { "year": "1974", "month": 10, "value": 272.35 },
  { "year": "1974", "month": 11, "value": 273.71 },
  { "year": "1974", "month": 12, "value": 274.2 },
  { "year": "1975", "month": 1, "value": 273.9 },
  { "year": "1975", "month": 2, "value": 275 },
  { "year": "1975", "month": 3, "value": 276.42 },
  { "year": "1975", "month": 4, "value": 276.17 },
  { "year": "1975", "month": 5, "value": 279.2 },
  { "year": "1975", "month": 6, "value": 282.43 },
  { "year": "1975", "month": 7, "value": 283.68 },
  { "year": "1975", "month": 8, "value": 284.15 },
  { "year": "1975", "month": 9, "value": 285.69 },
  { "year": "1975", "month": 10, "value": 285.39 },
  { "year": "1975", "month": 11, "value": 286.83 },
  { "year": "1975", "month": 12, "value": 287.07 },
  { "year": "1976", "month": 1, "value": 288.42 },
  { "year": "1976", "month": 2, "value": 290.76 },
  { "year": "1976", "month": 3, "value": 292.7 },
  { "year": "1976", "month": 4, "value": 294.66 },
  { "year": "1976", "month": 5, "value": 295.93 },
  { "year": "1976", "month": 6, "value": 296.16 },
  { "year": "1976", "month": 7, "value": 297.2 },
  { "year": "1976", "month": 8, "value": 299.05 },
  { "year": "1976", "month": 9, "value": 299.67 },
  { "year": "1976", "month": 10, "value": 302.04 },
  { "year": "1976", "month": 11, "value": 303.59 },
  { "year": "1976", "month": 12, "value": 306.25 },
  { "year": "1977", "month": 1, "value": 308.26 },
  { "year": "1977", "month": 2, "value": 311.54 },
  { "year": "1977", "month": 3, "value": 313.94 },
  { "year": "1977", "month": 4, "value": 316.02 },
  { "year": "1977", "month": 5, "value": 317.19 },
  { "year": "1977", "month": 6, "value": 318.71 },
  { "year": "1977", "month": 7, "value": 320.19 },
  { "year": "1977", "month": 8, "value": 322.27 },
  { "year": "1977", "month": 9, "value": 324.48 },
  { "year": "1977", "month": 10, "value": 326.4 },
  { "year": "1977", "month": 11, "value": 328.64 },
  { "year": "1977", "month": 12, "value": 330.87 },
  { "year": "1978", "month": 1, "value": 334.4 },
  { "year": "1978", "month": 2, "value": 335.3 },
  { "year": "1978", "month": 3, "value": 336.96 },
  { "year": "1978", "month": 4, "value": 339.92 },
  { "year": "1978", "month": 5, "value": 344.86 },
  { "year": "1978", "month": 6, "value": 346.8 },
  { "year": "1978", "month": 7, "value": 347.63 },
  { "year": "1978", "month": 8, "value": 349.66 },
  { "year": "1978", "month": 9, "value": 352.26 },
  { "year": "1978", "month": 10, "value": 353.35 },
  { "year": "1978", "month": 11, "value": 355.41 },
  { "year": "1978", "month": 12, "value": 357.28 },
  { "year": "1979", "month": 1, "value": 358.6 },
  { "year": "1979", "month": 2, "value": 359.91 },
  { "year": "1979", "month": 3, "value": 362.45 },
  { "year": "1979", "month": 4, "value": 368.05 },
  { "year": "1979", "month": 5, "value": 369.59 },
  { "year": "1979", "month": 6, "value": 373.34 },
  { "year": "1979", "month": 7, "value": 377.21 },
  { "year": "1979", "month": 8, "value": 378.82 },
  { "year": "1979", "month": 9, "value": 379.28 },
  { "year": "1979", "month": 10, "value": 380.87 },
  { "year": "1979", "month": 11, "value": 380.81 },
  { "year": "1979", "month": 12, "value": 381.77 },
  { "year": "1980", "month": 1, "value": 385.85 },
  { "year": "1980", "month": 2, "value": 389.7 },
  { "year": "1980", "month": 3, "value": 388.13 },
  { "year": "1980", "month": 4, "value": 383.44 },
  { "year": "1980", "month": 5, "value": 384.6 },
  { "year": "1980", "month": 6, "value": 389.46 },
  { "year": "1980", "month": 7, "value": 394.91 },
  { "year": "1980", "month": 8, "value": 400.06 },
  { "year": "1980", "month": 9, "value": 405.36 },
  { "year": "1980", "month": 10, "value": 409.06 },
  { "year": "1980", "month": 11, "value": 410.37 },
  { "year": "1980", "month": 12, "value": 408.06 },
  { "year": "1981", "month": 1, "value": 410.83 },
  { "year": "1981", "month": 2, "value": 414.38 },
  { "year": "1981", "month": 3, "value": 418.69 },
  { "year": "1981", "month": 4, "value": 427.06 },
  { "year": "1981", "month": 5, "value": 424.43 },
  { "year": "1981", "month": 6, "value": 425.5 },
  { "year": "1981", "month": 7, "value": 427.9 },
  { "year": "1981", "month": 8, "value": 427.85 },
  { "year": "1981", "month": 9, "value": 427.46 },
  { "year": "1981", "month": 10, "value": 428.45 },
  { "year": "1981", "month": 11, "value": 430.88 },
  { "year": "1981", "month": 12, "value": 436.17 },
  { "year": "1982", "month": 1, "value": 442.13 },
  { "year": "1982", "month": 2, "value": 441.49 },
  { "year": "1982", "month": 3, "value": 442.37 },
  { "year": "1982", "month": 4, "value": 446.78 },
  { "year": "1982", "month": 5, "value": 446.53 },
  { "year": "1982", "month": 6, "value": 447.89 },
  { "year": "1982", "month": 7, "value": 449.09 },
  { "year": "1982", "month": 8, "value": 452.49 },
  { "year": "1982", "month": 9, "value": 457.5 },
  { "year": "1982", "month": 10, "value": 464.57 },
  { "year": "1982", "month": 11, "value": 471.12 },
  { "year": "1982", "month": 12, "value": 474.3 },
  { "year": "1983", "month": 1, "value": 476.68 },
  { "year": "1983", "month": 2, "value": 483.85 },
  { "year": "1983", "month": 3, "value": 490.18 },
  { "year": "1983", "month": 4, "value": 492.77 },
  { "year": "1983", "month": 5, "value": 499.78 },
  { "year": "1983", "month": 6, "value": 504.35 },
  { "year": "1983", "month": 7, "value": 508.96 },
  { "year": "1983", "month": 8, "value": 511.6 },
  { "year": "1983", "month": 9, "value": 513.41 },
  { "year": "1983", "month": 10, "value": 517.21 },
  { "year": "1983", "month": 11, "value": 518.53 },
  { "year": "1983", "month": 12, "value": 520.79 },
  { "year": "1984", "month": 1, "value": 524.4 },
  { "year": "1984", "month": 2, "value": 526.99 },
  { "year": "1984", "month": 3, "value": 530.78 },
  { "year": "1984", "month": 4, "value": 534.03 },
  { "year": "1984", "month": 5, "value": 536.59 },
  { "year": "1984", "month": 6, "value": 540.54 },
  { "year": "1984", "month": 7, "value": 542.13 },
  { "year": "1984", "month": 8, "value": 542.39 },
  { "year": "1984", "month": 9, "value": 543.86 },
  { "year": "1984", "month": 10, "value": 543.87 },
  { "year": "1984", "month": 11, "value": 547.32 },
  { "year": "1984", "month": 12, "value": 551.19 },
  { "year": "1985", "month": 1, "value": 555.66 },
  { "year": "1985", "month": 2, "value": 562.48 },
  { "year": "1985", "month": 3, "value": 565.74 },
  { "year": "1985", "month": 4, "value": 569.55 },
  { "year": "1985", "month": 5, "value": 575.07 },
  { "year": "1985", "month": 6, "value": 583.17 },
  { "year": "1985", "month": 7, "value": 590.82 },
  { "year": "1985", "month": 8, "value": 598.06 },
  { "year": "1985", "month": 9, "value": 604.47 },
  { "year": "1985", "month": 10, "value": 607.91 },
  { "year": "1985", "month": 11, "value": 611.83 },
  { "year": "1985", "month": 12, "value": 619.36 },
  { "year": "1986", "month": 1, "value": 620.4 },
  { "year": "1986", "month": 2, "value": 624.14 },
  { "year": "1986", "month": 3, "value": 632.81 },
  { "year": "1986", "month": 4, "value": 640.35 },
  { "year": "1986", "month": 5, "value": 652.01 },
  { "year": "1986", "month": 6, "value": 661.52 },
  { "year": "1986", "month": 7, "value": 672.2 },
  { "year": "1986", "month": 8, "value": 680.77 },
  { "year": "1986", "month": 9, "value": 688.51 },
  { "year": "1986", "month": 10, "value": 695.26 },
  { "year": "1986", "month": 11, "value": 705.24 },
  { "year": "1986", "month": 12, "value": 724.28 },
  { "year": "1987", "month": 1, "value": 729.34 },
  { "year": "1987", "month": 2, "value": 729.84 },
  { "year": "1987", "month": 3, "value": 733.01 },
  { "year": "1987", "month": 4, "value": 743.39 },
  { "year": "1987", "month": 5, "value": 746 },
  { "year": "1987", "month": 6, "value": 743.72 },
  { "year": "1987", "month": 7, "value": 744.96 },
  { "year": "1987", "month": 8, "value": 746.96 },
  { "year": "1987", "month": 9, "value": 748.66 },
  { "year": "1987", "month": 10, "value": 756.5 },
  { "year": "1987", "month": 11, "value": 752.83 },
  { "year": "1987", "month": 12, "value": 749.68 },
  { "year": "1988", "month": 1, "value": 755.55 },
  { "year": "1988", "month": 2, "value": 757.07 },
  { "year": "1988", "month": 3, "value": 761.18 },
  { "year": "1988", "month": 4, "value": 767.57 },
  { "year": "1988", "month": 5, "value": 771.68 },
  { "year": "1988", "month": 6, "value": 779.1 },
  { "year": "1988", "month": 7, "value": 783.4 },
  { "year": "1988", "month": 8, "value": 785.08 },
  { "year": "1988", "month": 9, "value": 784.82 },
  { "year": "1988", "month": 10, "value": 783.63 },
  { "year": "1988", "month": 11, "value": 784.46 },
  { "year": "1988", "month": 12, "value": 786.26 },
  { "year": "1989", "month": 1, "value": 784.92 },
  { "year": "1989", "month": 2, "value": 783.4 },
  { "year": "1989", "month": 3, "value": 782.74 },
  { "year": "1989", "month": 4, "value": 778.82 },
  { "year": "1989", "month": 5, "value": 774.79 },
  { "year": "1989", "month": 6, "value": 774.22 },
  { "year": "1989", "month": 7, "value": 779.71 },
  { "year": "1989", "month": 8, "value": 781.14 },
  { "year": "1989", "month": 9, "value": 782.2 },
  { "year": "1989", "month": 10, "value": 787.05 },
  { "year": "1989", "month": 11, "value": 787.95 },
  { "year": "1989", "month": 12, "value": 792.57 },
  { "year": "1990", "month": 1, "value": 794.93 },
  { "year": "1990", "month": 2, "value": 797.65 },
  { "year": "1990", "month": 3, "value": 801.25 },
  { "year": "1990", "month": 4, "value": 806.24 },
  { "year": "1990", "month": 5, "value": 804.36 },
  { "year": "1990", "month": 6, "value": 810.33 },
  { "year": "1990", "month": 7, "value": 811.8 },
  { "year": "1990", "month": 8, "value": 817.85 },
  { "year": "1990", "month": 9, "value": 821.83 },
  { "year": "1990", "month": 10, "value": 820.3 },
  { "year": "1990", "month": 11, "value": 822.06 },
  { "year": "1990", "month": 12, "value": 824.56 },
  { "year": "1991", "month": 1, "value": 826.73 },
  { "year": "1991", "month": 2, "value": 832.4 },
  { "year": "1991", "month": 3, "value": 838.62 },
  { "year": "1991", "month": 4, "value": 842.73 },
  { "year": "1991", "month": 5, "value": 848.96 },
  { "year": "1991", "month": 6, "value": 858.33 },
  { "year": "1991", "month": 7, "value": 862.95 },
  { "year": "1991", "month": 8, "value": 868.65 },
  { "year": "1991", "month": 9, "value": 871.56 },
  { "year": "1991", "month": 10, "value": 878.4 },
  { "year": "1991", "month": 11, "value": 887.95 },
  { "year": "1991", "month": 12, "value": 896.7 },
  { "year": "1992", "month": 1, "value": 910.49 },
  { "year": "1992", "month": 2, "value": 925.13 },
  { "year": "1992", "month": 3, "value": 936 },
  { "year": "1992", "month": 4, "value": 943.89 },
  { "year": "1992", "month": 5, "value": 950.78 },
  { "year": "1992", "month": 6, "value": 954.71 },
  { "year": "1992", "month": 7, "value": 964.6 },
  { "year": "1992", "month": 8, "value": 975.71 },
  { "year": "1992", "month": 9, "value": 988.84 },
  { "year": "1992", "month": 10, "value": 1004.34 },
  { "year": "1992", "month": 11, "value": 1016.04 },
  { "year": "1992", "month": 12, "value": 1024.45 },
  { "year": "1993", "month": 1, "value": 1030.9 },
  { "year": "1993", "month": 2, "value": 1033.15 },
  { "year": "1993", "month": 3, "value": 1037.99 },
  { "year": "1993", "month": 4, "value": 1047.47 },
  { "year": "1993", "month": 5, "value": 1066.22 },
  { "year": "1993", "month": 6, "value": 1075.61 },
  { "year": "1993", "month": 7, "value": 1085.88 },
  { "year": "1993", "month": 8, "value": 1095.56 },
  { "year": "1993", "month": 9, "value": 1105.43 },
  { "year": "1993", "month": 10, "value": 1113.8 },
  { "year": "1993", "month": 11, "value": 1123.9 },
  { "year": "1993", "month": 12, "value": 1129.31 },
  { "year": "1994", "month": 1, "value": 1132.2 },
  { "year": "1994", "month": 2, "value": 1136.13 },
  { "year": "1994", "month": 3, "value": 1139.91 },
  { "year": "1994", "month": 4, "value": 1141.42 },
  { "year": "1994", "month": 5, "value": 1142.85 },
  { "year": "1994", "month": 6, "value": 1145.65 },
  { "year": "1994", "month": 7, "value": 1151.49 },
  { "year": "1994", "month": 8, "value": 1151.39 },
  { "year": "1994", "month": 9, "value": 1152.44 },
  { "year": "1994", "month": 10, "value": 1150.41 },
  { "year": "1994", "month": 11, "value": 1150.44 },
  { "year": "1994", "month": 12, "value": 1149.75 },
  { "year": "1995", "month": 1, "value": 1150.64 },
  { "year": "1995", "month": 2, "value": 1146.74 },
  { "year": "1995", "month": 3, "value": 1146.52 },
  { "year": "1995", "month": 4, "value": 1149.48 },
  { "year": "1995", "month": 5, "value": 1144.65 },
  { "year": "1995", "month": 6, "value": 1144.24 },
  { "year": "1995", "month": 7, "value": 1146.5 },
  { "year": "1995", "month": 8, "value": 1146.1 },
  { "year": "1995", "month": 9, "value": 1142.27 },
  { "year": "1995", "month": 10, "value": 1136.43 },
  { "year": "1995", "month": 11, "value": 1133.55 },
  { "year": "1995", "month": 12, "value": 1126.73 },
  { "year": "1996", "month": 1, "value": 1122.58 },
  { "year": "1996", "month": 2, "value": 1117.53 },
  { "year": "1996", "month": 3, "value": 1122.59 },
  { "year": "1996", "month": 4, "value": 1124.52 },
  { "year": "1996", "month": 5, "value": 1116.3 },
  { "year": "1996", "month": 6, "value": 1115.47 },
  { "year": "1996", "month": 7, "value": 1112.34 },
  { "year": "1996", "month": 8, "value": 1102.18 },
  { "year": "1996", "month": 9, "value": 1095.61 },
  { "year": "1996", "month": 10, "value": 1082.56 },
  { "year": "1996", "month": 11, "value": 1080.49 },
  { "year": "1996", "month": 12, "value": 1081.34 },
  { "year": "1997", "month": 1, "value": 1080.52 },
  { "year": "1997", "month": 2, "value": 1076.2 },
  { "year": "1997", "month": 3, "value": 1072.42 },
  { "year": "1997", "month": 4, "value": 1067.45 },
  { "year": "1997", "month": 5, "value": 1063.37 },
  { "year": "1997", "month": 6, "value": 1065.99 },
  { "year": "1997", "month": 7, "value": 1067.57 },
  { "year": "1997", "month": 8, "value": 1072.08 },
  { "year": "1997", "month": 9, "value": 1064.82 },
  { "year": "1997", "month": 10, "value": 1062.06 },
  { "year": "1997", "month": 11, "value": 1067.53 },
  { "year": "1997", "month": 12, "value": 1074.87 },
  { "year": "1998", "month": 1, "value": 1073.81 },
  { "year": "1998", "month": 2, "value": 1076.02 },
  { "year": "1998", "month": 3, "value": 1080.65 },
  { "year": "1998", "month": 4, "value": 1082.09 },
  { "year": "1998", "month": 5, "value": 1078.17 },
  { "year": "1998", "month": 6, "value": 1077.78 },
  { "year": "1998", "month": 7, "value": 1075.37 },
  { "year": "1998", "month": 8, "value": 1072.21 },
  { "year": "1998", "month": 9, "value": 1074.65 },
  { "year": "1998", "month": 10, "value": 1080.4 },
  { "year": "1998", "month": 11, "value": 1088.96 },
  { "year": "1998", "month": 12, "value": 1093.35 }
]
